{
  "_meta": {
    "sources": [
      "loopback/common/models",
      "loopback/server/models",
      "../common/models",
      "./models"
    ],
    "mixins": [
      "loopback/common/mixins",
      "loopback/server/mixins",
      "../common/mixins",
      "./mixins"
    ]
  },
  "User": {
    "dataSource": "mongo",
    "public": false
  },
  "AccessToken": {
    "dataSource": "mongo",
    "public": false
  },
  "ACL": {
    "dataSource": "mongo",
    "public": false
  },
  "RoleMapping": {
    "dataSource": "mongo",
    "public": false,
    "options": {
      "strictObjectIDCoercion": true
    }
  },
  "Role": {
    "dataSource": "mongo",
    "public": false
  },
  "speaker": {
    "dataSource": "mongo",
    "public": true
  },
  "event": {
    "dataSource": "mongo",
    "public": true
  },
  "talk": {
    "dataSource": "mongo",
    "public": true
  },
  "organizer": {
    "dataSource": "mongo",
    "public": true
  },
  "accessToken": {
    "dataSource": "mongo",
    "public": true,
    "relations": {
      "user": {
        "type": "belongsTo",
        "model": "organizer",
        "foreignKey": "organizerId"
      }
    }
  }
}
